CHANGES.txt
LICENSE.txt
MANIFEST.in
README.txt
setup.py
TanTan.egg-info/PKG-INFO
TanTan.egg-info/SOURCES.txt
TanTan.egg-info/dependency_links.txt
TanTan.egg-info/requires.txt
TanTan.egg-info/top_level.txt
tantan/__init__.py
tantan/agents.py
tantan/pans.py
tantan/service.py
tantan/uarts.py
tantan/utils.py
tantan/wamp.py
tantan/zigbee.py