Metadata-Version: 1.0
Name: TanTan
Version: 0.1.1
Summary: An open-source application for communicating with         Physical-Area-Networks using the ZigBee protocol
Home-page: https://pypi.python.org/pypi/TanTan
Author: Joaquin Rosales
Author-email: globojorro@gmail.com
License: LICENSE.txt
Platform: UNKNOWN
